Metadata-Version: 2.1
Name: clife-svc
Version: 1.20
Summary: A module for service
Home-page: UNKNOWN
Author: andy.hu
Author-email: hlp0@163.com
License: UNKNOWN
Platform: UNKNOWN
Classifier: Programming Language :: Python :: 3
Classifier: License :: OSI Approved :: MIT License
Classifier: Operating System :: OS Independent
Requires-Python: >=3.6
Requires-Dist: loguru (>=0.7.0)
Requires-Dist: aiohttp (>=3.8.4)
Requires-Dist: requests (<3,>=2.22.0)
Requires-Dist: fastapi (>=0.83.0)
Requires-Dist: uvicorn
Requires-Dist: cos-python-sdk-v5
Requires-Dist: orjson
Requires-Dist: contextvars
Requires-Dist: boto3
Requires-Dist: rocketmq (>=0.4.4)
Requires-Dist: gunicorn
